{
  "build": {
    "development-simulator": {
      "developmentClient": true,
      "distribution": "internal",
      "env": {
        "EXPO_PUBLIC_API_URL": "https://api.dev.betterangels.la",
        "EXPO_PUBLIC_REDIRECT_URL": "https://api.dev.betterangels.la/auth-redirect",
        "EXPO_PUBLIC_GOOGLE_CLIENT_ID": "1066399826613-bu41lbb5ha9fpgen895kic4bgebkn223.apps.googleusercontent.com"
      },
      "channel": "development",
      "ios": {
        "simulator": true
      },
      "node": "20.12.2"
    },
    "preview": {
      "distribution": "internal",
      "developmentClient": true,
      "env": {
        "EXPO_PUBLIC_API_URL": "https://api.dev.betterangels.la",
        "EXPO_PUBLIC_REDIRECT_URL": "https://api.dev.betterangels.la/auth-redirect",
        "EXPO_PUBLIC_GOOGLE_CLIENT_ID": "1066399826613-bu41lbb5ha9fpgen895kic4bgebkn223.apps.googleusercontent.com"
      },
      "node": "20.12.2"
    },
    "production": {
      "android": {
        "buildType": "app-bundle"
      },
      "env": {
        "APP_VARIANT": "production",
        "EXPO_PUBLIC_API_URL": "https://api.prod.betterangels.la",
        "EXPO_PUBLIC_REDIRECT_URL": "https://api.prod.betterangels.la/auth-redirect",
        "EXPO_PUBLIC_GOOGLE_CLIENT_ID": "243499089918-vtp6l4qrbrrgu8lhcqki7r9a34iu9rlv.apps.googleusercontent.com"
      },
      "channel": "production",
      "node": "20.12.2"
    }
  },
  "submit": {
    "production": {}
  },
  "cli": {
    "version": ">= 5"
  }
}
